{
    "songs": [
        {
            "name": "Tutorial",
            "icon": "gf",
            "bgColor": "#A5004D",
            "difficulties": [
                "Easy",
                "Normal",
                "Hard"
            ]
        },
        {
            "name": "Bopeebo",
            "icon": "dad",
            "bgColor": "#AF66CE",
            "difficulties": [
                "Easy",
                "Normal",
                "Hard"
            ]
        },
        {
            "name": "Fresh",
            "icon": "dad",
            "bgColor": "#AF66CE",
            "difficulties": [
                "Easy",
                "Normal",
                "Hard"
            ]
        },
        {
            "name": "Dad Battle",
            "icon": "dad",
            "bgColor": "#AF66CE",
            "difficulties": [
                "Easy",
                "Normal",
                "Hard"
            ]
        },
        {
            "name": "Spookeez",
            "icon": "spooky",
            "bgColor": "#D57E00",
            "difficulties": [
                "Easy",
                "Normal",
                "Hard"
            ]
        },
        {
            "name": "South",
            "icon": "spooky",
            "bgColor": "#D57E00",
            "difficulties": [
                "Easy",
                "Normal",
                "Hard"
            ]
        },
        {
            "name": "Monster",
            "icon": "monster",
            "bgColor": "#F3FF6E",
            "difficulties": [
                "Easy",
                "Normal",
                "Hard"
            ]
        },
        {
            "name": "Pico",
            "icon": "pico",
            "bgColor": "#B7D855",
            "difficulties": [
                "Easy",
                "Normal",
                "Hard"
            ]
        },
        {
            "name": "Philly Nice",
            "icon": "pico",
            "bgColor": "#B7D855",
            "difficulties": [
                "Easy",
                "Normal",
                "Hard"
            ]
        },
        {
            "name": "Blammed",
            "icon": "pico",
            "bgColor": "#B7D855",
            "difficulties": [
                "Easy",
                "Normal",
                "Hard"
            ]
        },
        {
            "name": "Satin Panties",
            "icon": "mom",
            "bgColor": "#D8558E",
            "difficulties": [
                "Easy",
                "Normal",
                "Hard"
            ]
        },
        {
            "name": "High",
            "icon": "mom",
            "bgColor": "#D8558E",
            "difficulties": [
                "Easy",
                "Normal",
                "Hard"
            ]
        },
        {
            "name": "M.I.L.F",
            "icon": "mom",
            "bgColor": "#D8558E",
            "difficulties": [
                "Easy",
                "Normal",
                "Hard"
            ]
        },
        {
            "name": "Cocoa",
            "icon": "parents-christmas",
            "bgColor": "#D8558E",
            "difficulties": [
                "Easy",
                "Normal",
                "Hard"
            ]
        },
        {
            "name": "Eggnog",
            "icon": "parents-christmas",
            "bgColor": "#D8558E",
            "difficulties": [
                "Easy",
                "Normal",
                "Hard"
            ]
        },
        {
            "name": "Winter Horrorland",
            "icon": "monster",
            "bgColor": "#F3FF6E",
            "difficulties": [
                "Easy",
                "Normal",
                "Hard"
            ]
        },
        {
            "name": "Senpai",
            "icon": "senpai",
            "bgColor": "#FFAA6F",
            "difficulties": [
                "Easy",
                "Normal",
                "Hard"
            ]
        },
        {
            "name": "Roses",
            "icon": "senpai",
            "bgColor": "#FFAA6F",
            "difficulties": [
                "Easy",
                "Normal",
                "Hard"
            ]
        },
        {
            "name": "Thorns",
            "icon": "spirit",
            "bgColor": "#FF3C6E",
            "difficulties": [
                "Easy",
                "Normal",
                "Hard"
            ]
        },
        {
            "name": "Test",
            "icon": "bf-pixel",
            "bgColor": "#31B0D1",
            "difficulties": [
                "Normal"
            ]
        }
    ]
}